llm_matrix/__init__.py
llm_matrix/aimodel.py
llm_matrix/cli.py
llm_matrix/converter.py
llm_matrix/mappings/relationship-to-task.yaml
llm_matrix/metrics.py
llm_matrix/plugins/__init__.py
llm_matrix/plugins/citeseek_plugin.py
llm_matrix/plugins/plugin.py
llm_matrix/runner.py
llm_matrix/schema.py
llm_matrix/store.py
llm_matrix/summary_stats.py
llm_matrix/utils.py
llm_matrix-0.1.3.dist-info/LICENSE
llm_matrix-0.1.3.dist-info/METADATA
llm_matrix-0.1.3.dist-info/WHEEL
llm_matrix-0.1.3.dist-info/entry_points.txt
llm_matrix-0.1.3.dist-info/RECORD
